{"0": "intent_0", "1": "intent_1", "2": "intent_10", "3": "intent_11", "4": "intent_12", "5": "intent_13", "6": "intent_14", "7": "intent_15", "8": "intent_16", "9": "intent_17", "10": "intent_18", "11": "intent_19", "12": "intent_2", "13": "intent_20", "14": "intent_21", "15": "intent_22", "16": "intent_23", "17": "intent_24", "18": "intent_25", "19": "intent_26", "20": "intent_27", "21": "intent_28", "22": "intent_29", "23": "intent_3", "24": "intent_30", "25": "intent_31", "26": "intent_32", "27": "intent_33", "28": "intent_34", "29": "intent_35", "30": "intent_36", "31": "intent_37", "32": "intent_38", "33": "intent_39", "34": "intent_4", "35": "intent_40", "36": "intent_41", "37": "intent_42", "38": "intent_43", "39": "intent_44", "40": "intent_45", "41": "intent_46", "42": "intent_47", "43": "intent_48", "44": "intent_49", "45": "intent_5", "46": "intent_50", "47": "intent_51", "48": "intent_52", "49": "intent_53", "50": "intent_54", "51": "intent_55", "52": "intent_56", "53": "intent_57", "54": "intent_58", "55": "intent_59", "56": "intent_6", "57": "intent_60", "58": "intent_61", "59": "intent_62", "60": "intent_63", "61": "intent_64", "62": "intent_65", "63": "intent_66", "64": "intent_67", "65": "intent_68", "66": "intent_69", "67": "intent_7", "68": "intent_70", "69": "intent_71", "70": "intent_72", "71": "intent_73", "72": "intent_74", "73": "intent_75", "74": "intent_76", "75": "intent_77", "76": "intent_78", "77": "intent_79", "78": "intent_8", "79": "intent_80", "80": "intent_9"}